[
  {"id": 401, "category": "Food", "question": "What is the main ingredient in guacamole?", "options": ["Tomato", "Avocado", "Cucumber", "Lime"], "answer": "B", "difficulty": "easy"},
  {"id": 402, "category": "Food", "question": "Which country is sushi originally from?", "options": ["China", "Korea", "Thailand", "Japan"], "answer": "D", "difficulty": "easy"},
  {"id": 403, "category": "Food", "question": "What type of pasta is shaped like small rice grains?", "options": ["Penne", "Orzo", "Fusilli", "Farfalle"], "answer": "B", "difficulty": "medium"},
  {"id": 404, "category": "Food", "question": "Which spice is known as the most expensive in the world?", "options": ["Vanilla", "Cardamom", "Saffron", "Truffle"], "answer": "C", "difficulty": "medium"},
  {"id": 405, "category": "Food", "question": "What is the primary ingredient in hummus?", "options": ["Lentils", "Black beans", "Chickpeas", "Kidney beans"], "answer": "C", "difficulty": "easy"},
  {"id": 406, "category": "Food", "question": "Which fruit is known as the 'King of Fruits' in Southeast Asia?", "options": ["Mango", "Durian", "Jackfruit", "Papaya"], "answer": "B", "difficulty": "medium"},
  {"id": 407, "category": "Food", "question": "What cooking technique involves submerging food in hot oil?", "options": ["Grilling", "Baking", "Deep frying", "Steaming"], "answer": "C", "difficulty": "easy"},
  {"id": 408, "category": "Food", "question": "What is the national dish of South Africa?", "options": ["Jollof Rice", "Bobotie", "Peri-Peri Chicken", "Biltong"], "answer": "B", "difficulty": "hard"},
  {"id": 409, "category": "Food", "question": "Which nut is used to make marzipan?", "options": ["Walnut", "Hazelnut", "Almond", "Cashew"], "answer": "C", "difficulty": "medium"},
  {"id": 410, "category": "Food", "question": "What is the Japanese dish of raw fish called?", "options": ["Tempura", "Sashimi", "Ramen", "Udon"], "answer": "B", "difficulty": "easy"},
  {"id": 411, "category": "Food", "question": "Which country invented croissants?", "options": ["France", "Austria", "Belgium", "Switzerland"], "answer": "B", "difficulty": "hard"},
  {"id": 412, "category": "Food", "question": "What gives bread its light and airy texture?", "options": ["Salt", "Sugar", "Yeast", "Butter"], "answer": "C", "difficulty": "easy"},
  {"id": 413, "category": "Food", "question": "Which vitamin is produced by the skin when exposed to sunlight?", "options": ["Vitamin A", "Vitamin B12", "Vitamin C", "Vitamin D"], "answer": "D", "difficulty": "medium"},
  {"id": 414, "category": "Food", "question": "What is the base spirit in a Margarita cocktail?", "options": ["Vodka", "Rum", "Tequila", "Gin"], "answer": "C", "difficulty": "easy"},
  {"id": 415, "category": "Food", "question": "What is the most consumed beverage in the world after water?", "options": ["Coffee", "Tea", "Cola", "Juice"], "answer": "B", "difficulty": "medium"},
  {"id": 416, "category": "Food", "question": "Which country is known for originating the dish 'Peri-Peri chicken'?", "options": ["South Africa", "Nigeria", "Mozambique", "Ghana"], "answer": "C", "difficulty": "hard"},
  {"id": 417, "category": "Food", "question": "What is a Bao?", "options": ["A type of ramen", "A steamed filled bun", "A crispy dumpling", "A rice dish"], "answer": "B", "difficulty": "medium"},
  {"id": 418, "category": "Food", "question": "What nut is used to make Nutella?", "options": ["Almond", "Cashew", "Hazelnut", "Walnut"], "answer": "C", "difficulty": "easy"},
  {"id": 419, "category": "Food", "question": "Which country does jollof rice originate from?", "options": ["Nigeria", "Ghana", "Senegal", "It is disputed"], "answer": "D", "difficulty": "hard"},
  {"id": 420, "category": "Food", "question": "What ingredient makes bread rise?", "options": ["Baking soda", "Yeast", "Flour", "Eggs"], "answer": "B", "difficulty": "easy"},
  {"id": 421, "category": "Food", "question": "What is the process of cooking food slowly in liquid called?", "options": ["Roasting", "Braising", "Grilling", "Blanching"], "answer": "B", "difficulty": "medium"},
  {"id": 422, "category": "Food", "question": "What is the Italian word for 'cheese'?", "options": ["Formaggio", "Fromage", "Queso", "Käse"], "answer": "A", "difficulty": "medium"},
  {"id": 423, "category": "Food", "question": "How many teaspoons are in a tablespoon?", "options": ["2", "3", "4", "5"], "answer": "B", "difficulty": "easy"},
  {"id": 424, "category": "Food", "question": "What fruit is used to make wine?", "options": ["Apple", "Pear", "Grape", "Plum"], "answer": "C", "difficulty": "easy"},
  {"id": 425, "category": "Food", "question": "What is the main flavouring in a traditional Caesar salad dressing?", "options": ["Blue cheese", "Ranch", "Anchovy and Parmesan", "Mustard and honey"], "answer": "C", "difficulty": "medium"},
  {"id": 426, "category": "Food", "question": "What is the main ingredient in miso soup?", "options": ["Tofu", "Seaweed", "Soybean paste", "Mushrooms"], "answer": "C", "difficulty": "medium"},
  {"id": 427, "category": "Food", "question": "Which country is known for its 'Croissant' pastry?", "options": ["Austria", "France", "Belgium", "Italy"], "answer": "A", "difficulty": "hard"},
  {"id": 428, "category": "Food", "question": "What is the name of the traditional Japanese tea ceremony?", "options": ["Chanoyu", "Sakura", "Zen", "Ikebana"], "answer": "A", "difficulty": "medium"},
  {"id": 429, "category": "Food", "question": "What does 'al dente' mean in cooking?", "options": ["Firm to the bite", "Very soft", "Overcooked", "Undercooked"], "answer": "A", "difficulty": "medium"},
  {"id": 430, "category": "Food", "question": "Which country is famous for its chocolate industry?", "options": ["Belgium", "Switzerland", "Netherlands", "All of the above"], "answer": "D", "difficulty": "easy"},
  {"id": 431, "category": "Food", "question": "What is the main ingredient in a traditional pesto sauce?", "options": ["Tomatoes", "Basil", "Garlic", "Pine nuts"], "answer": "B", "difficulty": "medium"},
  {"id": 432, "category": "Food", "question": "What is the name of the French dish of snails?", "options": ["Escargots", "Omelette", "Ratatouille", "Bouillabaisse"], "answer": "A", "difficulty": "easy"},
  {"id": 433, "category": "Food", "question": "Which fruit is known as the 'King of Fruits' in India?", "options": ["Mango", "Banana", "Apple", "Orange"], "answer": "A", "difficulty": "easy"},
  {"id": 434, "category": "Food", "question": "What is the national dish of Spain?", "options": ["Tapas", "Paella", "Gazpacho", "Tortilla"], "answer": "B", "difficulty": "easy"},
  {"id": 435, "category": "Food", "question": "What is the name of the Italian dish made with rice?", "options": ["Risotto", "Pasta", "Gnocchi", "Focaccia"], "answer": "A", "difficulty": "easy"},
  {"id": 436, "category": "Food", "question": "Which country is known for inventing the hot dog?", "options": ["Germany", "USA", "Austria", "Switzerland"], "answer": "A", "difficulty": "medium"},
  {"id": 437, "category": "Food", "question": "What is the main ingredient in a classic Caesar salad?", "options": ["Lettuce", "Chicken", "Cheese", "Bacon"], "answer": "A", "difficulty": "easy"},
  {"id": 438, "category": "Food", "question": "What type of cheese is used in a classic Margherita pizza?", "options": ["Cheddar", "Mozzarella", "Parmesan", "Feta"], "answer": "B", "difficulty": "easy"},
  {"id": 439, "category": "Food", "question": "What is the name of the dish made from pickled vegetables?", "options": ["Kimchi", "Sauerkraut", "Achar", "All of the above"], "answer": "D", "difficulty": "medium"},
  {"id": 440, "category": "Food", "question": "Which country is known for its traditional breakfast of Viennoiseries?", "options": ["Austria", "France", "Switzerland", "Belgium"], "answer": "A", "difficulty": "hard"},
  {"id": 441, "category": "Food", "question": "What is the process of fermenting tea leaves called?", "options": ["Oxidation", "Fermentation", "Aging", "Curing"], "answer": "B", "difficulty": "hard"},
  {"id": 442, "category": "Food", "question": "What is the name of the traditional English dish of meat and potatoes?", "options": ["Sunday Roast", "Stew", "Cottage Pie", "Bangers and Mash"], "answer": "D", "difficulty": "medium"},
  {"id": 443, "category": "Food", "question": "Which country is known for its cheese fondue?", "options": ["Switzerland", "France", "Italy", "Austria"], "answer": "A", "difficulty": "easy"},
  {"id": 444, "category": "Food", "question": "What is the main ingredient in the Indian dish 'Tandoori Chicken'?", "options": ["Chicken", "Lamb", "Fish", "Paneer"], "answer": "A", "difficulty": "easy"},
  {"id": 445, "category": "Food", "question": "What is the name of the Italian dessert made from ladyfingers and mascarpone?", "options": ["Panna Cotta", "Tiramisu", "Cannoli", "Zabaglione"], "answer": "B", "difficulty": "easy"},
  {"id": 446, "category": "Food", "question": "Which fruit is the main ingredient in a traditional Greek dish 'Tzatziki'?", "options": ["Cucumber", "Lemon", "Garlic", "Olive"], "answer": "A", "difficulty": "medium"},
  {"id": 447, "category": "Food", "question": "What is the name of the Japanese dish made with fermented soybeans?", "options": ["Miso", "Natto", "Tofu", "Soy Sauce"], "answer": "B", "difficulty": "hard"},
  {"id": 448, "category": "Food", "question": "Which country is known for its sweet pastry called 'Baklava'?", "options": ["Greece", "Turkey", "Egypt", "All of the above"], "answer": "D", "difficulty": "easy"},
  {"id": 449, "category": "Food", "question": "What is the main ingredient in the French dish 'Ratatouille'?", "options": ["Vegetables", "Meat", "Cheese", "Eggs"], "answer": "A", "difficulty": "easy"},
  {"id": 450, "category": "Food", "question": "What is the name of the traditional Italian cured meat?", "options": ["Prosciutto", "Salami", "Bresaola", "All of the above"], "answer": "D", "difficulty": "medium"},
  {"id": 451, "category": "Food", "question": "Which country is known for its Poutine dish?", "options": ["Canada", "USA", "UK", "France"], "answer": "A", "difficulty": "easy"},
  {"id": 452, "category": "Food", "question": "What is the name of the Spanish cold soup?", "options": ["Gazpacho", "Salmorejo", "Ajoblanco", "All of the above"], "answer": "D", "difficulty": "medium"},
  {"id": 453, "category": "Food", "question": "What is the main ingredient in the Thai dish 'Tom Yum'?", "options": ["Shrimp", "Chicken", "Fish", "Tofu"], "answer": "A", "difficulty": "medium"},
  {"id": 454, "category": "Food", "question": "Which country is known for its 'Kebabs'?", "options": ["Turkey", "Greece", "Iran", "All of the above"], "answer": "D", "difficulty": "easy"},
  {"id": 455, "category": "Food", "question": "What is the name of the Italian pasta sauce made with tomatoes and herbs?", "options": ["Marinara", "Alfredo", "Pesto", "Carbonara"], "answer": "A", "difficulty": "easy"},
  {"id": 456, "category": "Food", "question": "What is the main ingredient in the Moroccan dish 'Couscous'?", "options": ["Wheat", "Rice", "Barley", "Corn"], "answer": "A", "difficulty": "easy"},
  {"id": 457, "category": "Food", "question": "Which country is known for its 'Churros'?", "options": ["Spain", "Mexico", "Portugal", "All of the above"], "answer": "D", "difficulty": "easy"},
  {"id": 458, "category": "Food", "question": "What is the name of the traditional Chinese soup made from shark fin?", "options": ["Shark Fin Soup", "Bird's Nest Soup", "Wonton Soup", "Hot and Sour Soup"], "answer": "A", "difficulty": "hard"},
  {"id": 459, "category": "Food", "question": "What is the main ingredient in the dish 'Falafel'?", "options": ["Chickpeas", "Lentils", "Black beans", "Kidney beans"], "answer": "A", "difficulty": "easy"},
  {"id": 460, "category": "Food", "question": "Which country is known for its 'Käsespätzle'?", "options": ["Austria", "Germany", "Switzerland", "Hungary"], "answer": "B", "difficulty": "hard"},
  {"id": 461, "category": "Food", "question": "What is the name of the Italian dessert made with espresso and coffee?", "options": ["Tiramisu", "Panna Cotta", "Cannoli", "Zabaglione"], "answer": "A", "difficulty": "easy"},
  {"id": 462, "category": "Food", "question": "Which country is known for its 'Souvlaki'?", "options": ["Greece", "Turkey", "Lebanon", "Egypt"], "answer": "A", "difficulty": "easy"},
  {"id": 463, "category": "Food", "question": "What is the main ingredient in the dish 'Pâté'?", "options": ["Liver", "Meat", "Fish", "Vegetables"], "answer": "A", "difficulty": "medium"},
  {"id": 464, "category": "Food", "question": "What is the name of the French dish of mussels and fries?", "options": ["Moules Frites", "Coquilles Saint-Jacques", "Bouillabaisse", "Cassoulet"], "answer": "A", "difficulty": "medium"},
  {"id": 465, "category": "Food", "question": "Which country is known for its 'Falafel'?", "options": ["Egypt", "Israel", "Palestine", "All of the above"], "answer": "D", "difficulty": "easy"},
  {"id": 466, "category": "Food", "question": "What is the name of the traditional Scottish dish of sheep's stomach?", "options": ["Haggis", "Black Pudding", "Scotch Egg", "Cullen Skink"], "answer": "A", "difficulty": "hard"},
  {"id": 467, "category": "Food", "question": "What is the main ingredient in the dish 'Borscht'?", "options": ["Beetroot", "Cabbage", "Potato", "Carrot"], "answer": "A", "difficulty": "medium"},
  {"id": 468, "category": "Food", "question": "Which country is known for its 'Croque Monsieur'?", "options": ["France", "Belgium", "Switzerland", "Luxembourg"], "answer": "A", "difficulty": "easy"},
  {"id": 469, "category": "Food", "question": "What is the name of the traditional Italian bread?", "options": ["Ciabatta", "Focaccia", "Pizza", "Panini"], "answer": "A", "difficulty": "easy"},
  {"id": 470, "category": "Food", "question": "What is the main ingredient in the dish 'Tabbouleh'?", "options": ["Bulgur", "Parsley", "Tomato", "Onion"], "answer": "A", "difficulty": "medium"},
  {"id": 471, "category": "Food", "question": "Which country is known for its 'Zeljeznica'?", "options": ["Croatia", "Serbia", "Slovenia", "Montenegro"], "answer": "A", "difficulty": "hard"},
  {"id": 472, "category": "Food", "question": "What is the name of the traditional Japanese noodle soup?", "options": ["Ramen", "Udon", "Soba", "All of the above"], "answer": "D", "difficulty": "easy"},
  {"id": 473, "category": "Food", "question": "What is the main ingredient in the dish 'Kimchi'?", "options": ["Cabbage", "Radish", "Cucumber", "All of the above"], "answer": "D", "difficulty": "medium"},
  {"id": 474, "category": "Food", "question": "Which country is known for its 'Tapas'?", "options": ["Spain", "Portugal", "Italy", "Greece"], "answer": "A", "difficulty": "easy"},
  {"id": 475, "category": "Food", "question": "What is the name of the traditional English bread?", "options": ["Sourdough", "Baguette", "Ciabatta", "Brioche"], "answer": "A", "difficulty": "easy"},
  {"id": 476, "category": "Food", "question": "What is the main ingredient in the dish 'Moussaka'?", "options": ["Eggplant", "Potato", "Meat", "All of the above"], "answer": "D", "difficulty": "medium"},
  {"id": 477, "category": "Food", "question": "Which country is known for its 'Biltong'?", "options": ["South Africa", "Namibia", "Botswana", "All of the above"], "answer": "D", "difficulty": "easy"},
  {"id": 478, "category": "Food", "question": "What is the name of the traditional Indian bread?", "options": ["Naan", "Roti", "Chapati", "All of the above"], "answer": "D", "difficulty": "easy"},
  {"id": 479, "category": "Food", "question": "What is the main ingredient in the dish 'Haggis'?", "options": ["Sheep", "Pig", "Cow", "Chicken"], "answer": "A", "difficulty": "hard"},
  {"id": 480, "category": "Food", "question": "Which country is known for its 'Sfiha'?", "options": ["Syria", "Lebanon", "Israel", "Jordan"], "answer": "B", "difficulty": "hard"},
  {"id": 481, "category": "Food", "question": "What is the name of the traditional American bread?", "options": ["White Bread", "Rye", "Sourdough", "Cornbread"], "answer": "D", "difficulty": "easy"},
  {"id": 482, "category": "Food", "question": "What is the main ingredient in the dish 'Baba Ganoush'?", "options": ["Eggplant", "Tomato", "Cucumber", "Onion"], "answer": "A", "difficulty": "medium"},
  {"id": 483, "category": "Food", "question": "Which country is known for its 'Peking Duck'?", "options": ["China", "Japan", "Korea", "Vietnam"], "answer": "A", "difficulty": "easy"},
  {"id": 484, "category": "Food", "question": "What is the name of the traditional Italian dessert?", "options": ["Cannoli", "Panna Cotta", "Tiramisu", "All of the above"], "answer": "D", "difficulty": "easy"},
  {"id": 485, "category": "Food", "question": "What is the main ingredient in the dish 'Tostones'?", "options": ["Plantain", "Banana", "Cassava", "Yuca"], "answer": "A", "difficulty": "medium"},
  {"id": 486, "category": "Food", "question": "Which country is known for its 'Köttbullar'?", "options": ["Sweden", "Norway", "Denmark", "Finland"], "answer": "A", "difficulty": "easy"},
  {"id": 487, "category": "Food", "question": "What is the name of the traditional French dessert?", "options": ["Crème Brûlée", "Tarte Tatin", "Éclair", "All of the above"], "answer": "D", "difficulty": "easy"},
  {"id": 488, "category": "Food", "question": "What is the main ingredient in the dish 'Goulash'?", "options": ["Beef", "Pork", "Chicken", "Lamb"], "answer": "A", "difficulty": "medium"},
  {"id": 489, "category": "Food", "question": "Which country is known for its 'Lokma'?", "options": ["Turkey", "Greece", "Lebanon", "All of the above"], "answer": "D", "difficulty": "hard"},
  {"id": 490, "category": "Food", "question": "What is the name of the traditional German bread?", "options": ["Pumpernickel", "Rye", "Pretzel", "Bretzel"], "answer": "A", "difficulty": "medium"},
  {"id": 491, "category": "Food", "question": "What is the main ingredient in the dish 'Gamba'?", "options": ["Shrimp", "Lobster", "Crab", "Scallops"], "answer": "A", "difficulty": "hard"},
  {"id": 492, "category": "Food", "question": "Which country is known for its 'Baklava'?", "options": ["Turkey", "Greece", "Lebanon", "All of the above"], "answer": "D", "difficulty": "easy"},
  {"id": 493, "category": "Food", "question": "What is the name of the traditional Japanese dessert?", "options": ["Mochi", "Dango", "Dorayaki", "All of the above"], "answer": "D", "difficulty": "medium"},
  {"id": 494, "category": "Food", "question": "What is the main ingredient in the dish 'Falafel'?", "options": ["Chickpeas", "Lentils", "Black beans", "Kidney beans"], "answer": "A", "difficulty": "easy"},
  {"id": 495, "category": "Food", "question": "Which country is known for its 'Poutine'?", "options": ["Canada", "USA", "UK", "France"], "answer": "A", "difficulty": "easy"},
  {"id": 496, "category": "Food", "question": "What is the name of the traditional Spanish bread?", "options": ["Pan de Bono", "Pan de Maiz", "Pan de Teja", "Pan de Campo"], "answer": "A", "difficulty": "hard"},
  {"id": 497, "category": "Food", "question": "What is the main ingredient in the dish 'Baba Ghanoush'?", "options": ["Eggplant", "Tomato", "Cucumber", "Onion"], "answer": "A", "difficulty": "medium"},
  {"id": 498, "category": "Food", "question": "Which country is known for its 'Empanadas'?", "options": ["Argentina", "Chile", "Uruguay", "All of the above"], "answer": "D", "difficulty": "easy"},
  {"id": 499, "category": "Food", "question": "What is the name of the traditional Chinese bread?", "options": ["Pao", "Man Tou", "Cong You Bing", "Jian Bing"], "answer": "B", "difficulty": "hard"},
  {"id": 500, "category": "Food", "question": "What is the main ingredient in the dish 'Biriyani'?", "options": ["Rice", "Meat", "Spices", "All of the above"], "answer": "D", "difficulty": "medium"}
]